my_sdk/__init__.py
my_sdk/color.py
my_sdk/model.py
enochcolor-0.1.dist-info/METADATA
enochcolor-0.1.dist-info/WHEEL
enochcolor-0.1.dist-info/top_level.txt
enochcolor-0.1.dist-info/RECORD
