Metadata-Version: 2.1
Name: enochcolor
Version: 0.1
Summary: A brief description of your SDK
Home-page: https://github.com/enoch/my_sdk
Author: Think Different
Author-email: your.email@example.com
Classifier: Programming Language :: Python :: 3
Classifier: License :: OSI Approved :: MIT License
Classifier: Operating System :: OS Independent
Requires-Python: >=3.6
Requires-Dist: colour-science
